[
  {
    "id": "casablanca",
    "name": "Casablanca",
    "arabic": "الدار البيضاء",
    "status": "Disponible",
    "image": "assets/morocco-casablanca-tee.png",
    "product": {
      "id": "morocco-casablanca-tee",
      "name": "Morocco Casablanca T-shirt",
      "price": 490,
      "currency": "MAD",
      "sizes": ["S", "M", "L", "XL"]
    }
  },
  { "id": "essaouira", "name": "Essaouira", "arabic": "الصويرة", "status": "Photos a venir" },
  { "id": "tanger", "name": "Tanger", "arabic": "طنجة", "status": "Photos a venir" },
  { "id": "kettama", "name": "Kettama", "arabic": "كتامة", "status": "Photos a venir" },
  { "id": "fes", "name": "Fes", "arabic": "فاس", "status": "Photos a venir" },
  { "id": "chaouenne", "name": "Chaouenne", "arabic": "شفشاون", "status": "Photos a venir" },
  { "id": "rabat", "name": "Rabat", "arabic": "الرباط", "status": "Photos a venir" },
  { "id": "agadir", "name": "Agadir", "arabic": "أكادير", "status": "Photos a venir" },
  { "id": "dakhla", "name": "Dakhla", "arabic": "الداخلة", "status": "Photos a venir" },
  { "id": "marrakech", "name": "Marrakech", "arabic": "مراكش", "status": "Photos a venir" }
]
